LICENSE
README.md
setup.py
src/pyRandomMedia/__init__.py
src/pyRandomMedia/pyMediaFunctions.py
src/pyRandomMedia/songs_file.py
src/pyRandomMedia.egg-info/PKG-INFO
src/pyRandomMedia.egg-info/SOURCES.txt
src/pyRandomMedia.egg-info/dependency_links.txt
src/pyRandomMedia.egg-info/requires.txt
src/pyRandomMedia.egg-info/top_level.txt
src/pyrandommedia/__init__.py
src/pyrandommedia/pyMediaFunctions.py
src/pyrandommedia/songs_file.py
src/pyrandommedia.egg-info/PKG-INFO
src/pyrandommedia.egg-info/SOURCES.txt
src/pyrandommedia.egg-info/dependency_links.txt
src/pyrandommedia.egg-info/requires.txt
src/pyrandommedia.egg-info/top_level.txt
tests/test_pyRandomMedia.py