Metadata-Version: 2.1
Name: pyrandommedia
Version: 0.0.5
Summary: A package used to generate random media for website testing. This includes songs, movies, news and Tv shows.
Home-page: https://github.com/software-students-spring2024/3-python-package-exercise-team-kiwi
Author: Stan, Nicholas, Benson, Sangely
License: UNKNOWN
Project-URL: Github Repo, https://github.com/software-students-spring2024/3-python-package-exercise-team-kiwi
Platform: UNKNOWN
Classifier: Programming Language :: Python :: 3
Classifier: License :: OSI Approved :: MIT License
Requires-Python: >=3.6
